CHANGES.txt
LICENSE.txt
MANIFEST.in
requirements.txt
setup.py
LightWriter.egg-info/PKG-INFO
LightWriter.egg-info/SOURCES.txt
LightWriter.egg-info/dependency_links.txt
LightWriter.egg-info/requires.txt
LightWriter.egg-info/top_level.txt
bin/example.py
lightwriter/Frame.py
lightwriter/LightWriter.py
lightwriter/__init__.py