Metadata-Version: 1.0
Name: LightWriter
Version: 1.0.6
Summary: Control a RadioShack Light Strip with an Arduino and Python
Home-page: http://pypi.python.org/pypi/LightWriter/
Author: Mike Kadin
Author-email: michaelkadin@gmail.com
License: LICENSE.txt
Platform: UNKNOWN
